trollius_redis/__init__.py
trollius_redis/connection.py
trollius_redis/cursors.py
trollius_redis/encoders.py
trollius_redis/exceptions.py
trollius_redis/log.py
trollius_redis/pool.py
trollius_redis/protocol.py
trollius_redis/replies.py
trollius_redis-0.1.4.dist-info/DESCRIPTION.rst
trollius_redis-0.1.4.dist-info/METADATA
trollius_redis-0.1.4.dist-info/metadata.json
trollius_redis-0.1.4.dist-info/RECORD
trollius_redis-0.1.4.dist-info/top_level.txt
trollius_redis-0.1.4.dist-info/WHEEL
