Metadata-Version: 2.0
Name: trollius-redis
Version: 0.1.4
Summary: PEP 3156 implementation of the redis protocol.
Home-page: https://github.com/benjolitz/trollius-redis
Author: Ben Jolitz
Author-email: ben.jolitz+trollius_redis@gmail.com
License: LICENSE.txt
Platform: UNKNOWN
Classifier: Development Status :: 4 - Beta
Classifier: Intended Audience :: Developers
Classifier: Topic :: Database
Classifier: License :: OSI Approved :: BSD License
Classifier: Programming Language :: Python :: 2
Classifier: Programming Language :: Python :: 2.7
Classifier: Programming Language :: Python :: 3
Classifier: Programming Language :: Python :: 3.3
Classifier: Programming Language :: Python :: 3.4
Requires-Dist: trollius
Requires-Dist: six
Requires-Dist: mock
Requires-Dist: hiredis
